guestbook/__init__.py
guestbook/static/main.css
guestbook/templates/index.html
guestbook_pro-1.0.0.dist-info/DESCRIPTION.rst
guestbook_pro-1.0.0.dist-info/METADATA
guestbook_pro-1.0.0.dist-info/RECORD
guestbook_pro-1.0.0.dist-info/WHEEL
guestbook_pro-1.0.0.dist-info/entry_points.txt
guestbook_pro-1.0.0.dist-info/metadata.json
guestbook_pro-1.0.0.dist-info/top_level.txt
