Metadata-Version: 2.0
Name: guestbook-pro
Version: 1.0.0
Summary: An enterprise guestbook web application.
Home-page: https://github.com/anl-mcampos/GuestBook.git
Author: anl-mcampos
Author-email: fedhelp@anl.gov
License: MIT License
Keywords: web,guestbook,anl
Platform: UNKNOWN
Classifier: Development Status :: 5 - Production/Stable
Classifier: Framework :: Flask
Classifier: License :: OSI Approved :: MIT License
Classifier: Programming Language :: Python
Classifier: Programming Language :: Python :: 2.6
Classifier: Programming Language :: Python :: 2.7
Classifier: Programming Language :: Python :: 3
Classifier: Programming Language :: Python :: 3.2
Classifier: Programming Language :: Python :: 3.3
Classifier: Programming Language :: Python :: 3.4
Classifier: Programming Language :: Python :: 3.5
Requires-Dist: Flask
Requires-Dist: click
Requires-Dist: netifaces
